hugit/__init__.py
hugit/cli.py
hugit/console.py
hugit/convert.py
hugit/core.py
hugit/image_dataset.py
hugit/project.toml
hugit/py.typed
hugit-0.1.1.dist-info/entry_points.txt
hugit-0.1.1.dist-info/LICENSE
hugit-0.1.1.dist-info/WHEEL
hugit-0.1.1.dist-info/METADATA
hugit-0.1.1.dist-info/RECORD
