Metadata-Version: 2.1
Name: hugit
Version: 0.1.1
Summary: Hugit
Home-page: https://github.com/davanstrien/hugit-cli
License: MIT
Author: Daniel van Strien
Author-email: daniel.van-strien@bl.uk
Requires-Python: >=3.8,<4.0.0
Classifier: Development Status :: 2 - Pre-Alpha
Classifier: License :: OSI Approved :: MIT License
Classifier: Programming Language :: Python :: 3
Classifier: Programming Language :: Python :: 3.8
Classifier: Programming Language :: Python :: 3.9
Classifier: Programming Language :: Python :: 3.10
Classifier: Programming Language :: Python :: 3.11
Requires-Dist: Pillow (>=9.1.1,<10.0.0)
Requires-Dist: attrs (>=22.1.0,<23.0.0)
Requires-Dist: click (>=8.1.0,<9.0.0)
Requires-Dist: datasets (>=2.0.0,<3.0.0)
Requires-Dist: rich (>=12.0.1,<13.0.0)
Requires-Dist: rich-click (>=1.5.2,<2.0.0)
Requires-Dist: toolz (>=0.11.2,<0.12.0)
Requires-Dist: typed-settings (>=1.0.0,<2.0.0)
Requires-Dist: typing-extensions (>=4.1.1,<5.0.0)
Project-URL: Changelog, https://github.com/davanstrien/hugit/releases
Project-URL: Documentation, https://hugit.readthedocs.io
Project-URL: Repository, https://github.com/davanstrien/hugit-cli
